{
  "ProviderId": "Microsoft.VisualStudio.ConnectedService.Wcf",
  "Version": "15.0.31022.994",
  "ExtendedData": {
    "inputs": [
      "http://192.168.81.70:8089/icws.asmx"
    ],
    "collectionTypes": [
      "System.Array",
      "System.Collections.Generic.Dictionary`2"
    ],
    "messageContract": true,
    "namespaceMappings": [
      "*, LsiService"
    ],
    "references": [
      "Newtonsoft.Json, {Newtonsoft.Json, 12.0.3}",
      "System.ServiceModel, {System.ServiceModel.Primitives, 4.4.4}",
      "System.ServiceModel.Duplex, {System.ServiceModel.Duplex, 4.4.4}",
      "System.ServiceModel.Http, {System.ServiceModel.Http, 4.4.4}",
      "System.ServiceModel.NetTcp, {System.ServiceModel.NetTcp, 4.4.4}",
      "System.ServiceModel.Primitives, {System.ServiceModel.Primitives, 4.4.4}",
      "System.ServiceModel.Security, {System.ServiceModel.Security, 4.4.4}"
    ],
    "sync": true,
    "targetFramework": "netstandard2.0",
    "typeReuseMode": "All"
  }
}